pandas/__init__.py
pandas/_typing.py
pandas/_version.py
pandas/conftest.py
pandas/meson.build
pandas/testing.py
pandas/_config/__init__.py
pandas/_config/config.py
pandas/_config/dates.py
pandas/_config/display.py
pandas/_config/localization.py
pandas/_libs/__init__.py
pandas/_libs/algos.cpython-312.so
pandas/_libs/algos.pxd
pandas/_libs/algos.pyi
pandas/_libs/algos.pyx
pandas/_libs/algos_common_helper.pxi.in
pandas/_libs/algos_take_helper.pxi.in
pandas/_libs/arrays.cpython-312.so
pandas/_libs/arrays.pxd
pandas/_libs/arrays.pyi
pandas/_libs/arrays.pyx
pandas/_libs/byteswap.cpython-312.so
pandas/_libs/byteswap.pyi
pandas/_libs/byteswap.pyx
pandas/_libs/dtypes.pxd
pandas/_libs/groupby.cpython-312.so
pandas/_libs/groupby.pyi
pandas/_libs/groupby.pyx
pandas/_libs/hashing.cpython-312.so
pandas/_libs/hashing.pyi
pandas/_libs/hashing.pyx
pandas/_libs/hashtable.cpython-312.so
pandas/_libs/hashtable.pxd
pandas/_libs/hashtable.pyi
pandas/_libs/hashtable.pyx
pandas/_libs/hashtable_class_helper.pxi.in
pandas/_libs/hashtable_func_helper.pxi.in
pandas/_libs/index.cpython-312.so
pandas/_libs/index.pyi
pandas/_libs/index.pyx
pandas/_libs/index_class_helper.pxi.in
pandas/_libs/indexing.cpython-312.so
pandas/_libs/indexing.pyi
pandas/_libs/indexing.pyx
pandas/_libs/internals.cpython-312.so
pandas/_libs/internals.pyi
pandas/_libs/internals.pyx
pandas/_libs/interval.cpython-312.so
pandas/_libs/interval.pyi
pandas/_libs/interval.pyx
pandas/_libs/intervaltree.pxi.in
pandas/_libs/join.cpython-312.so
pandas/_libs/join.pyi
pandas/_libs/join.pyx
pandas/_libs/json.cpython-312.so
pandas/_libs/json.pyi
pandas/_libs/khash.pxd
pandas/_libs/khash_for_primitive_helper.pxi.in
pandas/_libs/lib.cpython-312.so
pandas/_libs/lib.pxd
pandas/_libs/lib.pyi
pandas/_libs/lib.pyx
pandas/_libs/meson.build
pandas/_libs/missing.cpython-312.so
pandas/_libs/missing.pxd
pandas/_libs/missing.pyi
pandas/_libs/missing.pyx
pandas/_libs/ops.cpython-312.so
pandas/_libs/ops.pyi
pandas/_libs/ops.pyx
pandas_aipy-2.2.3.dist-info/METADATA
pandas_aipy-2.2.3.dist-info/WHEEL
pandas_aipy-2.2.3.dist-info/top_level.txt
pandas_aipy-2.2.3.dist-info/RECORD
